httpsrequests/__init__.py
httpsrequests/httpsrequests_file.py
httpsrequests-1.dist-info/METADATA
httpsrequests-1.dist-info/WHEEL
httpsrequests-1.dist-info/top_level.txt
httpsrequests-1.dist-info/RECORD
